Metadata-Version: 2.1
Name: lzmysample
Version: 0.1
Summary: My Python package
Author: lz
Author-email: jhs012@gmail.com
